asgi_htmx/__init__.py
asgi_htmx/_middleware.py
asgi_htmx/_models.py
asgi_htmx/_requests.py
asgi_htmx/_types.py
asgi_htmx/py.typed
asgi_htmx-0.1.0.dist-info/LICENSE
asgi_htmx-0.1.0.dist-info/METADATA
asgi_htmx-0.1.0.dist-info/WHEEL
asgi_htmx-0.1.0.dist-info/top_level.txt
asgi_htmx-0.1.0.dist-info/RECORD
