Metadata-Version: 2.1
Name: asgi-htmx
Version: 0.1.0
Summary: HTMX integration for ASGI applications.
Author-email: Florimond Manca <florimond.manca@protonmail.com>
License: MIT
Project-URL: Homepage, https://github.com/florimondmanca/asgi-htmx
Classifier: Development Status :: 3 - Alpha
Classifier: Intended Audience :: Developers
Classifier: Framework :: AsyncIO
Classifier: Programming Language :: Python :: 3
Classifier: Programming Language :: Python :: 3 :: Only
Classifier: Programming Language :: Python :: 3.8
Classifier: Programming Language :: Python :: 3.9
Classifier: Programming Language :: Python :: 3.10
Requires-Python: >=3.8
License-File: LICENSE
